tssplit/__init__.py
tssplit/py.typed
tssplit/tssplit.py
tssplit-1.0.9.dist-info/LICENSE
tssplit-1.0.9.dist-info/METADATA
tssplit-1.0.9.dist-info/WHEEL
tssplit-1.0.9.dist-info/top_level.txt
tssplit-1.0.9.dist-info/RECORD
