Metadata-Version: 2.1
Name: tssplit
Version: 1.0.9
Summary: Trivial split for strings with quotes and escaped characters
Home-page: https://github.com/mezantrop/tssplit
Author: Mikhail Zakharov
Author-email: zmey20000@yahoo.com
License: bsd-2-clause
Keywords: split,parse,quote,trim,strip,string,delimiter,separator
Classifier: License :: OSI Approved :: BSD License
Classifier: Development Status :: 5 - Production/Stable
Classifier: Intended Audience :: Developers
Classifier: Operating System :: OS Independent
Classifier: Programming Language :: Python :: 3
Classifier: Topic :: Software Development
Classifier: Topic :: Text Processing
Classifier: Topic :: Text Processing :: Filters
Classifier: Topic :: Text Processing :: General
License-File: LICENSE
